MANIFEST.in
README.rst
setup.py
docs/HISTORY.txt
docs/LICENSE.GPL
docs/LICENSE.txt
opengever/__init__.py
opengever.mysqlconfig.egg-info/PKG-INFO
opengever.mysqlconfig.egg-info/SOURCES.txt
opengever.mysqlconfig.egg-info/dependency_links.txt
opengever.mysqlconfig.egg-info/entry_points.txt
opengever.mysqlconfig.egg-info/namespace_packages.txt
opengever.mysqlconfig.egg-info/not-zip-safe
opengever.mysqlconfig.egg-info/requires.txt
opengever.mysqlconfig.egg-info/top_level.txt
opengever/mysqlconfig/__init__.py
opengever/mysqlconfig/configure.zcml
opengever/mysqlconfig/create_database.sql
opengever/mysqlconfig/dev.zcml
opengever/mysqlconfig/dev_create_database.sql