Metadata-Version: 1.0
Name: opengever.mysqlconfig
Version: 1.1.2
Summary: configures the mysql as database engine
Home-page: https://github.com/4teamwork/opengever.mysqlconfig
Author: 4teamwork AG
Author-email: mailto:info@4teamwork.ch
License: GPL2
Keywords: opengever mysql config
Platform: UNKNOWN
Classifier: Framework :: Plone
Classifier: Framework :: Zope2
Classifier: Framework :: Zope3
Classifier: Programming Language :: Python
Classifier: Topic :: Software Development :: Libraries :: Python Modules
